jbag/__init__.py
jbag/config.py
jbag/io.py
jbag/log.py
jbag/metric_summary.py
jbag/parallel_map.py
jbag/statistics.py
jbag/clustering/__init__.py
jbag/clustering/agglomerative_hierarchical_clustering.py
jbag/converters/__init__.py
jbag/converters/dicom2nifti.py
jbag/converters/nifti2dicom.py
jbag/dicom/__init__.py
jbag/dicom/dicom.py
jbag/dicom/dicom_tags.py
jbag/dicom/modalities.py
jbag/docx/__init__.py
jbag/docx/doc.py
jbag/docx/image.py
jbag/docx/paragraph.py
jbag/docx/table.py
jbag/docx/text.py
jbag/improc/__init__.py
jbag/improc/colors.py
jbag/improc/contrast_enhancement.py
jbag/improc/gaussian_filter.py
jbag/improc/label_utils.py
jbag/improc/overlay.py
jbag/metrics/SDF.py
jbag/metrics/__init__.py
jbag/metrics/distances.py
jbag/models/__init__.py
jbag/models/deep_supervision.py
jbag/models/mlp.py
jbag/models/network_weight_initialization.py
jbag/models/unet.py
jbag/models/unet_plus_plus.py
jbag/models/utils.py
jbag/samplers/__init__.py
jbag/samplers/coordinate_generator.py
jbag/samplers/grid_sampler.py
jbag/samplers/patch_picker.py
jbag/samplers/preload_data_loader.py
jbag/samplers/preload_dataset.py
jbag/samplers/utils.py
jbag/torchkit/__init__.py
jbag/torchkit/checkpoint_manager.py
jbag/torchkit/lr.py
jbag/transforms/__init__.py
jbag/transforms/_utils.py
jbag/transforms/brightness.py
jbag/transforms/contrast.py
jbag/transforms/data.py
jbag/transforms/distance.py
jbag/transforms/downsample.py
jbag/transforms/gamma.py
jbag/transforms/gaussian_blur.py
jbag/transforms/gaussian_noise.py
jbag/transforms/mirroring.py
jbag/transforms/normalization.py
jbag/transforms/spatial.py
jbag/transforms/transform.py
jbag-4.5.3.dist-info/METADATA
jbag-4.5.3.dist-info/WHEEL
jbag-4.5.3.dist-info/RECORD
