Metadata-Version: 2.4
Name: jbag
Version: 4.5.3
Summary: Tools for medical image processing and deep learning.
Author-email: Dai Jian <daijian@stumail.ysu.edu.cn>
License-Expression: MIT
Classifier: Programming Language :: Python :: 3.11
Requires-Python: >=3.11
Requires-Dist: dicom2nifti>=2.4.8
Requires-Dist: nibabel>=4.0.1
Requires-Dist: numpy>=1.21.0
Requires-Dist: openpyxl
Requires-Dist: pandas
Requires-Dist: pydicom>=2.4.3
Requires-Dist: python-docx
Requires-Dist: scikit-image
Requires-Dist: scipy>=1.7.3
Requires-Dist: simpleitk>=2.1.1.2
